Metadata-Version: 1.1
Name: Popet
Version: 0.0.1
Summary: The Useless Easy Tool to Handle Pope's Data
Home-page: https://github.com/delta114514/Popet
Author: Yamato Nagata
Author-email: chickenwingswillfly@gmail.com
License: MIT
Platform: any
Classifier: Development Status :: 3 - Alpha
Classifier: Environment :: Other Environment
Classifier: Intended Audience :: Developers
Classifier: License :: OSI Approved :: MIT License
Classifier: Operating System :: OS Independent
Classifier: Programming Language :: Python :: 3
Classifier: Programming Language :: Python
Classifier: Topic :: Software Development :: Libraries :: Python Modules
